tpauth/__init__.py
tpauth/endpoint.py
tpauth/response/base.py
tpauth/response/success.py
tpauth/response/unauthorised.py
tpauth/response/unknown.py
tpauth/tpauth.py
tpauth-1.0.0.dist-info/LICENSE
tpauth-1.0.0.dist-info/WHEEL
tpauth-1.0.0.dist-info/METADATA
tpauth-1.0.0.dist-info/RECORD
